{
  "scriptCompleted": true,
  "contentDigest": "ae58b750ed17562c719399cf539e61a9fb4308ca2b74416bcb1c9b42ebf8589b",
  "files": [
    {
      "path": ".ua/.understandignore",
      "language": "unknown",
      "sizeLines": 68,
      "fileCategory": "code"
    },
    {
      "path": ".ua/config.json",
      "language": "json",
      "sizeLines": 3,
      "fileCategory": "config"
    },
    {
      "path": "README.md",
      "language": "markdown",
      "sizeLines": 55,
      "fileCategory": "docs"
    },
    {
      "path": "api/delete.js",
      "language": "javascript",
      "sizeLines": 32,
      "fileCategory": "code"
    },
    {
      "path": "api/favorites.js",
      "language": "javascript",
      "sizeLines": 52,
      "fileCategory": "code"
    },
    {
      "path": "api/list.js",
      "language": "javascript",
      "sizeLines": 34,
      "fileCategory": "code"
    },
    {
      "path": "api/migrate-vault.js",
      "language": "javascript",
      "sizeLines": 72,
      "fileCategory": "code"
    },
    {
      "path": "api/save-meta.js",
      "language": "javascript",
      "sizeLines": 70,
      "fileCategory": "code"
    },
    {
      "path": "api/upload.js",
      "language": "javascript",
      "sizeLines": 45,
      "fileCategory": "code"
    },
    {
      "path": "eslint.config.js",
      "language": "javascript",
      "sizeLines": 37,
      "fileCategory": "code"
    },
    {
      "path": "index.html",
      "language": "html",
      "sizeLines": 13,
      "fileCategory": "markup"
    },
    {
      "path": "lib/cloud.js",
      "language": "javascript",
      "sizeLines": 28,
      "fileCategory": "code"
    },
    {
      "path": "package.json",
      "language": "json",
      "sizeLines": 40,
      "fileCategory": "config"
    },
    {
      "path": "postcss.config.js",
      "language": "javascript",
      "sizeLines": 6,
      "fileCategory": "code"
    },
    {
      "path": "public/ffmpeg/ffmpeg-core.js",
      "language": "javascript",
      "sizeLines": 15,
      "fileCategory": "code"
    },
    {
      "path": "public/ffmpeg/ffmpeg-core.wasm",
      "language": "wasm",
      "sizeLines": 277426,
      "fileCategory": "code"
    },
    {
      "path": "src/App.jsx",
      "language": "javascript",
      "sizeLines": 996,
      "fileCategory": "code"
    },
    {
      "path": "src/buildInfo.js",
      "language": "javascript",
      "sizeLines": 3,
      "fileCategory": "code"
    },
    {
      "path": "src/components/CacheHistoryModal.jsx",
      "language": "javascript",
      "sizeLines": 282,
      "fileCategory": "code"
    },
    {
      "path": "src/components/ClozeDrill.jsx",
      "language": "javascript",
      "sizeLines": 126,
      "fileCategory": "code"
    },
    {
      "path": "src/components/ConfirmModal.jsx",
      "language": "javascript",
      "sizeLines": 38,
      "fileCategory": "code"
    },
    {
      "path": "src/components/EmptyState.jsx",
      "language": "javascript",
      "sizeLines": 225,
      "fileCategory": "code"
    },
    {
      "path": "src/components/ErrorBoundary.jsx",
      "language": "javascript",
      "sizeLines": 34,
      "fileCategory": "code"
    },
    {
      "path": "src/components/NoActiveFile.jsx",
      "language": "javascript",
      "sizeLines": 37,
      "fileCategory": "code"
    },
    {
      "path": "src/components/PassphraseGate.jsx",
      "language": "javascript",
      "sizeLines": 61,
      "fileCategory": "code"
    },
    {
      "path": "src/components/PlayerControls.jsx",
      "language": "javascript",
      "sizeLines": 276,
      "fileCategory": "code"
    },
    {
      "path": "src/components/SettingsModal.jsx",
      "language": "javascript",
      "sizeLines": 529,
      "fileCategory": "code"
    },
    {
      "path": "src/components/ShortcutsHelp.jsx",
      "language": "javascript",
      "sizeLines": 53,
      "fileCategory": "code"
    },
    {
      "path": "src/components/Toast.jsx",
      "language": "javascript",
      "sizeLines": 37,
      "fileCategory": "code"
    },
    {
      "path": "src/components/TranscriptItem.jsx",
      "language": "javascript",
      "sizeLines": 245,
      "fileCategory": "code"
    },
    {
      "path": "src/components/TrashModal.jsx",
      "language": "javascript",
      "sizeLines": 79,
      "fileCategory": "code"
    },
    {
      "path": "src/components/WorkspaceHeader.jsx",
      "language": "javascript",
      "sizeLines": 75,
      "fileCategory": "code"
    },
    {
      "path": "src/constants/models.js",
      "language": "javascript",
      "sizeLines": 69,
      "fileCategory": "code"
    },
    {
      "path": "src/hooks/useAppUpdate.js",
      "language": "javascript",
      "sizeLines": 42,
      "fileCategory": "code"
    },
    {
      "path": "src/hooks/useAudioPlayer.js",
      "language": "javascript",
      "sizeLines": 482,
      "fileCategory": "code"
    },
    {
      "path": "src/hooks/useEscapeToClose.js",
      "language": "javascript",
      "sizeLines": 34,
      "fileCategory": "code"
    },
    {
      "path": "src/hooks/useFavorites.js",
      "language": "javascript",
      "sizeLines": 80,
      "fileCategory": "code"
    },
    {
      "path": "src/hooks/useKeyboardShortcuts.js",
      "language": "javascript",
      "sizeLines": 105,
      "fileCategory": "code"
    },
    {
      "path": "src/hooks/useLearningProgress.js",
      "language": "javascript",
      "sizeLines": 77,
      "fileCategory": "code"
    },
    {
      "path": "src/hooks/useMediaAnalysis.js",
      "language": "javascript",
      "sizeLines": 1050,
      "fileCategory": "code"
    },
    {
      "path": "src/hooks/useMediaCache.js",
      "language": "javascript",
      "sizeLines": 445,
      "fileCategory": "code"
    },
    {
      "path": "src/hooks/useSettings.js",
      "language": "javascript",
      "sizeLines": 82,
      "fileCategory": "code"
    },
    {
      "path": "src/index.css",
      "language": "css",
      "sizeLines": 36,
      "fileCategory": "markup"
    },
    {
      "path": "src/main.jsx",
      "language": "javascript",
      "sizeLines": 10,
      "fileCategory": "code"
    },
    {
      "path": "src/services/cloudSync.js",
      "language": "javascript",
      "sizeLines": 127,
      "fileCategory": "code"
    },
    {
      "path": "src/services/gemini.js",
      "language": "javascript",
      "sizeLines": 1135,
      "fileCategory": "code"
    },
    {
      "path": "src/services/prompts.js",
      "language": "javascript",
      "sizeLines": 99,
      "fileCategory": "code"
    },
    {
      "path": "src/utils/MediaStore.js",
      "language": "javascript",
      "sizeLines": 169,
      "fileCategory": "code"
    },
    {
      "path": "src/utils/analysisParser.js",
      "language": "javascript",
      "sizeLines": 20,
      "fileCategory": "code"
    },
    {
      "path": "src/utils/audioExtractor.js",
      "language": "javascript",
      "sizeLines": 513,
      "fileCategory": "code"
    },
    {
      "path": "src/utils/cacheStatus.js",
      "language": "javascript",
      "sizeLines": 34,
      "fileCategory": "code"
    },
    {
      "path": "src/utils/cacheUtils.js",
      "language": "javascript",
      "sizeLines": 68,
      "fileCategory": "code"
    },
    {
      "path": "src/utils/clozeUtils.js",
      "language": "javascript",
      "sizeLines": 60,
      "fileCategory": "code"
    },
    {
      "path": "src/utils/languageUtils.js",
      "language": "javascript",
      "sizeLines": 86,
      "fileCategory": "code"
    },
    {
      "path": "src/utils/loopGroups.js",
      "language": "javascript",
      "sizeLines": 44,
      "fileCategory": "code"
    },
    {
      "path": "src/utils/materializeFile.js",
      "language": "javascript",
      "sizeLines": 84,
      "fileCategory": "code"
    },
    {
      "path": "src/utils/mediaUtils.js",
      "language": "javascript",
      "sizeLines": 140,
      "fileCategory": "code"
    },
    {
      "path": "src/utils/sentenceSplitter.js",
      "language": "javascript",
      "sizeLines": 120,
      "fileCategory": "code"
    },
    {
      "path": "src/utils/timeUtils.js",
      "language": "javascript",
      "sizeLines": 38,
      "fileCategory": "code"
    },
    {
      "path": "src/utils/trashUtils.js",
      "language": "javascript",
      "sizeLines": 53,
      "fileCategory": "code"
    },
    {
      "path": "src/utils/viewPosition.js",
      "language": "javascript",
      "sizeLines": 31,
      "fileCategory": "code"
    },
    {
      "path": "tailwind.config.js",
      "language": "javascript",
      "sizeLines": 11,
      "fileCategory": "code"
    },
    {
      "path": "vercel.json",
      "language": "json",
      "sizeLines": 6,
      "fileCategory": "config"
    },
    {
      "path": "vite.config.js",
      "language": "javascript",
      "sizeLines": 39,
      "fileCategory": "code"
    },
    {
      "path": "배포_가이드.md",
      "language": "markdown",
      "sizeLines": 114,
      "fileCategory": "docs"
    }
  ],
  "totalFiles": 65,
  "filteredByIgnore": 0,
  "estimatedComplexity": "moderate",
  "stats": {
    "filesScanned": 65,
    "byCategory": {
      "code": 58,
      "config": 3,
      "docs": 2,
      "markup": 2
    },
    "byLanguage": {
      "unknown": 1,
      "json": 3,
      "markdown": 2,
      "javascript": 56,
      "html": 1,
      "wasm": 1,
      "css": 1
    }
  }
}